multilevel_panels/__init__.py
multilevel_panels/multilevel_panels.py
multilevel_panels-0.1.dist-info/LICENSE.txt
multilevel_panels-0.1.dist-info/METADATA
multilevel_panels-0.1.dist-info/WHEEL
multilevel_panels-0.1.dist-info/top_level.txt
multilevel_panels-0.1.dist-info/RECORD
