Metadata-Version: 2.1
Name: multilevel-panels
Version: 0.1
Summary: A package for set logic on hierarchical data
Home-page: https://github.com/langelgjm/multilevel-panels
Author: Gabriel J. Michael
Author-email: gabriel.j.michael@gmail.com
License: MIT
Platform: UNKNOWN
Classifier: Development Status :: 3 - Alpha
Classifier: Intended Audience :: Developers
Classifier: License :: OSI Approved :: MIT License
Classifier: Programming Language :: Python :: 3.5
Requires-Dist: numpy (>=1.13)
